{"title":"The Martian","uid":12957911,"size":1602838528,"categoryP":"video","categoryS":"movies","magnet":"?xt=urn:btih:03205974e1a49393cf2d8a97e22d5bc5c412798a&amp;dn=+The+Martian&amp;tr=udp%3A%2F%2Ftracker.leechers-paradise.org%3A6969&amp;tr=udp%3A%2F%2Fzer0day.ch%3A1337&amp;tr=udp%3A%2F%2Fopen.demonii.com%3A1337&amp;tr=udp%3A%2F%2Ftracker.coppersurfer.tk%3A6969&amp;tr=udp%3A%2F%2Fexodus.desync.com%3A6969","seeders":0,"leechers":1,"uploader":"elbadaoui","files":1,"time":1449808504,"description":"\nThe Martian\r\nHDTS Quality | FRENCH | his MD\r\n\r\nOrigin of the film: American\r\nDirector: Ridley Scott\r\nStarring: Matt Damon, Jessica Chastain, Kristen Wiig\r\nGenre: Science fiction\r\nDuration: 2h24min\r\nRelease Date: 21 October 2015\r\nProduction year: 2015\r\nOriginal Title: The Martian\r\nDistributed by Twentieth Century Fox France\r\nPress Note: Only Mars 3.5 / 5\r\nNote spectators: Only on Mars 4.1 / 5 (7683)\r\n\r\n\r\n\r\n\r\n\r\nDuring a manned mission to Mars, Astronaut Mark Watney is presumed dead after a fierce storm and left behind by his crew. But Watney has survived and finds himself stranded and alone on the hostile planet. With only meager supplies, he must draw upon his ingenuity, wit and spirit to subsist and find a way to signal to Earth that he is alive.\r\n\r\n\r\nimage\r\n\r\nFormat: XviD\r\nThe.Martian.2015.FRENCH.HDTS.MD.XViD-EVO (1500 Mo)","torrent":{"xt":"urn:btih:03205974e1a49393cf2d8a97e22d5bc5c412798a","amp;dn":"+The+Martian","amp;tr":["udp%3A%2F%2Ftracker.leechers-paradise.org%3A6969","udp%3A%2F%2Fzer0day.ch%3A1337","udp%3A%2F%2Fopen.demonii.com%3A1337","udp%3A%2F%2Ftracker.coppersurfer.tk%3A6969","udp%3A%2F%2Fexodus.desync.com%3A6969"],"infoHash":"03205974e1a49393cf2d8a97e22d5bc5c412798a","infoHashBuffer":{"type":"Buffer","data":[3,32,89,116,225,164,147,147,207,45,138,151,226,45,91,197,196,18,121,138]},"announce":[],"urlList":[]}}