{"title":"LIAR'S CLUB -- with Betty White, Buddy Hackett, Larry Hovis","uid":12676733,"size":95132820,"categoryP":"video","categoryS":"tv_shows","magnet":"?xt=urn:btih:0ea232cd5ef66ef18482ea681b94fb959d47933c&amp;dn=LIAR%27S+CLUB+--+with+Betty+White%2C+Buddy+Hackett%2C+Larry+Hovis&amp;tr=udp%3A%2F%2Ftracker.leechers-paradise.org%3A6969&amp;tr=udp%3A%2F%2Fzer0day.ch%3A1337&amp;tr=udp%3A%2F%2Fopen.demonii.com%3A1337&amp;tr=udp%3A%2F%2Ftracker.coppersurfer.tk%3A6969&amp;tr=udp%3A%2F%2Fexodus.desync.com%3A6969","seeders":0,"leechers":1,"uploader":"TheExecutive","files":1,"time":1446511647,"description":"","torrent":{"xt":"urn:btih:0ea232cd5ef66ef18482ea681b94fb959d47933c","amp;dn":"LIAR%27S+CLUB+--+with+Betty+White%2C+Buddy+Hackett%2C+Larry+Hovis","amp;tr":["udp%3A%2F%2Ftracker.leechers-paradise.org%3A6969","udp%3A%2F%2Fzer0day.ch%3A1337","udp%3A%2F%2Fopen.demonii.com%3A1337","udp%3A%2F%2Ftracker.coppersurfer.tk%3A6969","udp%3A%2F%2Fexodus.desync.com%3A6969"],"infoHash":"0ea232cd5ef66ef18482ea681b94fb959d47933c","infoHashBuffer":{"type":"Buffer","data":[14,162,50,205,94,246,110,241,132,130,234,104,27,148,251,149,157,71,147,60]},"announce":[],"urlList":[]}}