{"title":"[8ThStreetLatinas] 2015-11-06 - Missy Martinez - Big Trouble Mis","uid":12705874,"size":3027013749,"categoryP":"porn","categoryS":"hd___movies","magnet":"?xt=urn:btih:15da45dcd1766e827510f084aa9b956732152cd5&amp;dn=%5B8ThStreetLatinas%5D+2015-11-06+-+Missy+Martinez+-+Big+Trouble+Mis&amp;tr=udp%3A%2F%2Ftracker.leechers-paradise.org%3A6969&amp;tr=udp%3A%2F%2Fzer0day.ch%3A1337&amp;tr=udp%3A%2F%2Fopen.demonii.com%3A1337&amp;tr=udp%3A%2F%2Ftracker.coppersurfer.tk%3A6969&amp;tr=udp%3A%2F%2Fexodus.desync.com%3A6969","seeders":0,"leechers":0,"uploader":"Piratepr0n","files":1,"time":1446825633,"description":"-------------------------------------------------------------------------------------\nName:\n[8ThStreetLatinas] 2015-11-06 - Missy Martinez - Big Trouble Missy [mp4][1920x1080]\n-------------------------------------------------------------------------------------\nFile list:\n8thsl.15.11.06.missy.martinez.big.trouble.missy.mp4 (2.82 GiB | 1920x1080 | 39min 35s | MPEG-4) \nhttp://imgfapper.com/img-563cc087a399e.html","torrent":{"xt":"urn:btih:15da45dcd1766e827510f084aa9b956732152cd5","amp;dn":"%5B8ThStreetLatinas%5D+2015-11-06+-+Missy+Martinez+-+Big+Trouble+Mis","amp;tr":["udp%3A%2F%2Ftracker.leechers-paradise.org%3A6969","udp%3A%2F%2Fzer0day.ch%3A1337","udp%3A%2F%2Fopen.demonii.com%3A1337","udp%3A%2F%2Ftracker.coppersurfer.tk%3A6969","udp%3A%2F%2Fexodus.desync.com%3A6969"],"infoHash":"15da45dcd1766e827510f084aa9b956732152cd5","infoHashBuffer":{"type":"Buffer","data":[21,218,69,220,209,118,110,130,117,16,240,132,170,155,149,103,50,21,44,213]},"announce":[],"urlList":[]}}