{"title":"PornMegaLoad.15.11.06.Nikky.Wilder.Get.Wilder.XXX.1080p.MP4-KTR","uid":12864910,"size":1202694709,"categoryP":"porn","categoryS":"hd___movies","magnet":"?xt=urn:btih:1776720f8ce9582d37235535c0258c9a8a969299&amp;dn=PornMegaLoad.15.11.06.Nikky.Wilder.Get.Wilder.XXX.1080p.MP4-KTR&amp;tr=udp%3A%2F%2Ftracker.leechers-paradise.org%3A6969&amp;tr=udp%3A%2F%2Fzer0day.ch%3A1337&amp;tr=udp%3A%2F%2Fopen.demonii.com%3A1337&amp;tr=udp%3A%2F%2Ftracker.coppersurfer.tk%3A6969&amp;tr=udp%3A%2F%2Fexodus.desync.com%3A6969","seeders":0,"leechers":1,"uploader":"0-DayXXX","files":1,"time":1448785994,"description":"http://youpornbook.com\n---------------------------------------\nPornMegaLoad.15.11.06.Nikky.Wilder.Get.Wilder.XXX.1080p.MP4-KTR\n---------------------------------------\nScreenshot(s): \nhttp://imgsay.com/?v=494253.jpg\n\n---------------------------------------\nInfo(s):\nFormat:\t\tMPEG-4\nSize:\t\t1.12 GiB\nDuration:\t19min 48s\nResolution:\t1920x1080\nBitrate:\t8000Kbps\n---------------------------------------\nIf you like this torrent, please post a comment!\nDon't forget to seed!","torrent":{"xt":"urn:btih:1776720f8ce9582d37235535c0258c9a8a969299","amp;dn":"PornMegaLoad.15.11.06.Nikky.Wilder.Get.Wilder.XXX.1080p.MP4-KTR","amp;tr":["udp%3A%2F%2Ftracker.leechers-paradise.org%3A6969","udp%3A%2F%2Fzer0day.ch%3A1337","udp%3A%2F%2Fopen.demonii.com%3A1337","udp%3A%2F%2Ftracker.coppersurfer.tk%3A6969","udp%3A%2F%2Fexodus.desync.com%3A6969"],"infoHash":"1776720f8ce9582d37235535c0258c9a8a969299","infoHashBuffer":{"type":"Buffer","data":[23,118,114,15,140,233,88,45,55,35,85,53,192,37,140,154,138,150,146,153]},"announce":[],"urlList":[]}}