{"title":"LadyboysFuckedBareBack - Bella 3 (Big Boobs and Booty Shorts Cum","uid":12667649,"size":1180085654,"categoryP":"porn","categoryS":"hd___movies","magnet":"?xt=urn:btih:265b2c58ef3d8803c3aad578aaeb0547d322cdec&amp;dn=LadyboysFuckedBareBack+-+Bella+3+%28Big+Boobs+and+Booty+Shorts+Cum&amp;tr=udp%3A%2F%2Ftracker.leechers-paradise.org%3A6969&amp;tr=udp%3A%2F%2Fzer0day.ch%3A1337&amp;tr=udp%3A%2F%2Fopen.demonii.com%3A1337&amp;tr=udp%3A%2F%2Ftracker.coppersurfer.tk%3A6969&amp;tr=udp%3A%2F%2Fexodus.desync.com%3A6969","seeders":0,"leechers":1,"uploader":"EndYou","files":1,"time":1446388914,"description":"~~~~~~~~~~~~~\r\n~Screenshots~\r\n~~~~~~~~~~~~~ \nhttp://imgpremium.com/image/ZK5 \nhttp://imgpremium.com/image/ZKA \r\n\r\n~~~~~~~~~~~~~\r\n~Description~\r\n~~~~~~~~~~~~~\r\nThe name of the actress: Bella 3\r\nName movie: Big Boobs &amp; Booty Shorts Cum Re-Insert\r\nNPP site and the site: LadyboysFuckedBareBack.com\r\n\r\nYear: 2015\r\nGenre: Ladyboy, Anal Sex\r\nDuration: 00:30:10\r\n\r\nVideo Format: MP4\r\nVideo: MPEG4 Video (H264) 1280x720 29.97fps 5019kbps\r\nAudio: AAC 44100Hz stereo 189kbps","torrent":{"xt":"urn:btih:265b2c58ef3d8803c3aad578aaeb0547d322cdec","amp;dn":"LadyboysFuckedBareBack+-+Bella+3+%28Big+Boobs+and+Booty+Shorts+Cum","amp;tr":["udp%3A%2F%2Ftracker.leechers-paradise.org%3A6969","udp%3A%2F%2Fzer0day.ch%3A1337","udp%3A%2F%2Fopen.demonii.com%3A1337","udp%3A%2F%2Ftracker.coppersurfer.tk%3A6969","udp%3A%2F%2Fexodus.desync.com%3A6969"],"infoHash":"265b2c58ef3d8803c3aad578aaeb0547d322cdec","infoHashBuffer":{"type":"Buffer","data":[38,91,44,88,239,61,136,3,195,170,213,120,170,235,5,71,211,34,205,236]},"announce":[],"urlList":[]}}