{"title":"German Teen step sister pov give handjob massage","uid":12687771,"size":138157152,"categoryP":"porn","categoryS":"movie_clips","magnet":"?xt=urn:btih:3536eb615e8ff7b81555d14c69d157bca8eb28c8&amp;dn=German+Teen+step+sister+pov+give+handjob+massage&amp;tr=udp%3A%2F%2Ftracker.leechers-paradise.org%3A6969&amp;tr=udp%3A%2F%2Fzer0day.ch%3A1337&amp;tr=udp%3A%2F%2Fopen.demonii.com%3A1337&amp;tr=udp%3A%2F%2Ftracker.coppersurfer.tk%3A6969&amp;tr=udp%3A%2F%2Fexodus.desync.com%3A6969","seeders":0,"leechers":1,"uploader":"demonoidt","files":1,"time":1446630168,"description":"Samples\r\n \nhttp://demonoid.co/2015/11/04/german-teen-step-sister-pov-give-handjob-massage/\r\n \nhttp://demonoid.co/2015/11/04/german-teen-step-sister-pov-give-handjob-massage-2/\r\n \nhttp://demonoid.co/2015/11/04/german-teen-step-sister-pov-give-handjob-massage-3/","torrent":{"xt":"urn:btih:3536eb615e8ff7b81555d14c69d157bca8eb28c8","amp;dn":"German+Teen+step+sister+pov+give+handjob+massage","amp;tr":["udp%3A%2F%2Ftracker.leechers-paradise.org%3A6969","udp%3A%2F%2Fzer0day.ch%3A1337","udp%3A%2F%2Fopen.demonii.com%3A1337","udp%3A%2F%2Ftracker.coppersurfer.tk%3A6969","udp%3A%2F%2Fexodus.desync.com%3A6969"],"infoHash":"3536eb615e8ff7b81555d14c69d157bca8eb28c8","infoHashBuffer":{"type":"Buffer","data":[53,54,235,97,94,143,247,184,21,85,209,76,105,209,87,188,168,235,40,200]},"announce":[],"urlList":[]}}