{"title":"Six Part Invention - Always and Ever (2015) [SWZ]","uid":12811545,"size":82043799,"categoryP":"audio","categoryS":"other","magnet":"?xt=urn:btih:38703d1422120f3d2c2c788aaa2f5777a867fde0&amp;dn=Six+Part+Invention+-+Always+and+Ever+%282015%29+%5BSWZ%5D&amp;tr=udp%3A%2F%2Ftracker.leechers-paradise.org%3A6969&amp;tr=udp%3A%2F%2Fzer0day.ch%3A1337&amp;tr=udp%3A%2F%2Fopen.demonii.com%3A1337&amp;tr=udp%3A%2F%2Ftracker.coppersurfer.tk%3A6969&amp;tr=udp%3A%2F%2Fexodus.desync.com%3A6969","seeders":0,"leechers":1,"uploader":"SkilletWarez","files":8,"time":1448188329,"description":"Artist: Six Part Invention \r\nAlbum: Always and Ever \r\nReleased: 2015\r\nGenres: Pop\r\nBit Rate: 320Kbps AAC M4A\r\nCopyright : (p) 2015 Universal Records\r\n\r\n\r\nT R A C K L I S T\r\n*******************************\r\n\r\n01 Feelings Don't Last\r\n02 I'll Never Go\r\n03 Always and Ever\r\n04 Kung Hindi Ngayon, Kailan Pa\r\n05 Sentimental Boulevard\r\n06 Take This Part\r\n07 Mine\r\n08 Time Machine\r\n\r\n*******************************","torrent":{"xt":"urn:btih:38703d1422120f3d2c2c788aaa2f5777a867fde0","amp;dn":"Six+Part+Invention+-+Always+and+Ever+%282015%29+%5BSWZ%5D","amp;tr":["udp%3A%2F%2Ftracker.leechers-paradise.org%3A6969","udp%3A%2F%2Fzer0day.ch%3A1337","udp%3A%2F%2Fopen.demonii.com%3A1337","udp%3A%2F%2Ftracker.coppersurfer.tk%3A6969","udp%3A%2F%2Fexodus.desync.com%3A6969"],"infoHash":"38703d1422120f3d2c2c788aaa2f5777a867fde0","infoHashBuffer":{"type":"Buffer","data":[56,112,61,20,34,18,15,61,44,44,120,138,170,47,87,119,168,103,253,224]},"announce":[],"urlList":[]}}