{"title":"Modern Living","uid":12877300,"size":199002439,"categoryP":"porn","categoryS":"movie_clips","magnet":"?xt=urn:btih:4ee160b26cdfbe2b5bd8bce6087162952d834c91&amp;dn=Modern+Living&amp;tr=udp%3A%2F%2Ftracker.leechers-paradise.org%3A6969&amp;tr=udp%3A%2F%2Fzer0day.ch%3A1337&amp;tr=udp%3A%2F%2Fopen.demonii.com%3A1337&amp;tr=udp%3A%2F%2Ftracker.coppersurfer.tk%3A6969&amp;tr=udp%3A%2F%2Fexodus.desync.com%3A6969","seeders":0,"leechers":0,"uploader":"demonoidt","files":1,"time":1448971315,"description":"Samples\r\n \nhttp://adultwallpapers.co.in/modern-living/\r\n \nhttp://adultwallpapers.co.in/modern-living-2/\r\n \nhttp://adultwallpapers.co.in/modern-living-3/\r\n \nhttp://demonoid.co/2015/12/01/modern-living/","torrent":{"xt":"urn:btih:4ee160b26cdfbe2b5bd8bce6087162952d834c91","amp;dn":"Modern+Living","amp;tr":["udp%3A%2F%2Ftracker.leechers-paradise.org%3A6969","udp%3A%2F%2Fzer0day.ch%3A1337","udp%3A%2F%2Fopen.demonii.com%3A1337","udp%3A%2F%2Ftracker.coppersurfer.tk%3A6969","udp%3A%2F%2Fexodus.desync.com%3A6969"],"infoHash":"4ee160b26cdfbe2b5bd8bce6087162952d834c91","infoHashBuffer":{"type":"Buffer","data":[78,225,96,178,108,223,190,43,91,216,188,230,8,113,98,149,45,131,76,145]},"announce":[],"urlList":[]}}