{"title":"AuntJudys Catrina Interview XXX 1080p (November 29, 2015)","uid":12867731,"size":508247451,"categoryP":"porn","categoryS":"hd___movies","magnet":"?xt=urn:btih:5026681d8d89f844e5277a2ca727f359c7adf192&amp;dn=AuntJudys+Catrina+Interview+XXX+1080p+%28November+29%2C+2015%29&amp;tr=udp%3A%2F%2Ftracker.leechers-paradise.org%3A6969&amp;tr=udp%3A%2F%2Fzer0day.ch%3A1337&amp;tr=udp%3A%2F%2Fopen.demonii.com%3A1337&amp;tr=udp%3A%2F%2Ftracker.coppersurfer.tk%3A6969&amp;tr=udp%3A%2F%2Fexodus.desync.com%3A6969","seeders":0,"leechers":1,"uploader":"thfatboys","files":1,"time":1448835317,"description":"Screens: \nhttp://imgpeak.com/img-565b52d3e5e78.html","torrent":{"xt":"urn:btih:5026681d8d89f844e5277a2ca727f359c7adf192","amp;dn":"AuntJudys+Catrina+Interview+XXX+1080p+%28November+29%2C+2015%29","amp;tr":["udp%3A%2F%2Ftracker.leechers-paradise.org%3A6969","udp%3A%2F%2Fzer0day.ch%3A1337","udp%3A%2F%2Fopen.demonii.com%3A1337","udp%3A%2F%2Ftracker.coppersurfer.tk%3A6969","udp%3A%2F%2Fexodus.desync.com%3A6969"],"infoHash":"5026681d8d89f844e5277a2ca727f359c7adf192","infoHashBuffer":{"type":"Buffer","data":[80,38,104,29,141,137,248,68,229,39,122,44,167,39,243,89,199,173,241,146]},"announce":[],"urlList":[]}}