{"title":"[2002] Small Town Ecstasy - Documentary","uid":12699463,"size":232249996,"categoryP":"video","categoryS":"tv_shows","magnet":"?xt=urn:btih:5aebe09e10a7d3d574f662b0e5667fe2e47be27d&amp;dn=%5B2002%5D+Small+Town+Ecstasy+-+Documentary&amp;tr=udp%3A%2F%2Ftracker.leechers-paradise.org%3A6969&amp;tr=udp%3A%2F%2Fzer0day.ch%3A1337&amp;tr=udp%3A%2F%2Fopen.demonii.com%3A1337&amp;tr=udp%3A%2F%2Ftracker.coppersurfer.tk%3A6969&amp;tr=udp%3A%2F%2Fexodus.desync.com%3A6969","seeders":0,"leechers":1,"uploader":"MilkEyedMint","files":2,"time":1446755071,"description":"Ripped from:\nIMDB: http://www.imdb.com/title/tt0337719/\r\n\r\nA good and apparently fairly rare documentary about ecstasy that follows a dad in his 40s and his children who all start using ecstasy","torrent":{"xt":"urn:btih:5aebe09e10a7d3d574f662b0e5667fe2e47be27d","amp;dn":"%5B2002%5D+Small+Town+Ecstasy+-+Documentary","amp;tr":["udp%3A%2F%2Ftracker.leechers-paradise.org%3A6969","udp%3A%2F%2Fzer0day.ch%3A1337","udp%3A%2F%2Fopen.demonii.com%3A1337","udp%3A%2F%2Ftracker.coppersurfer.tk%3A6969","udp%3A%2F%2Fexodus.desync.com%3A6969"],"infoHash":"5aebe09e10a7d3d574f662b0e5667fe2e47be27d","infoHashBuffer":{"type":"Buffer","data":[90,235,224,158,16,167,211,213,116,246,98,176,229,102,127,226,228,123,226,125]},"announce":[],"urlList":[]}}