{"title":"Marvel.Super.Hero.Adventures.Frost.2015.HDRip.XviD.AC3-EVO","uid":12990502,"size":1494957150,"categoryP":"video","categoryS":"movies","magnet":"?xt=urn:btih:5bc1ee37caa97f7b9ea10fe65ed5ead0c878d7e8&amp;dn=Marvel.Super.Hero.Adventures.Frost.2015.HDRip.XviD.AC3-EVO&amp;tr=udp%3A%2F%2Ftracker.leechers-paradise.org%3A6969&amp;tr=udp%3A%2F%2Fzer0day.ch%3A1337&amp;tr=udp%3A%2F%2Fopen.demonii.com%3A1337&amp;tr=udp%3A%2F%2Ftracker.coppersurfer.tk%3A6969&amp;tr=udp%3A%2F%2Fexodus.desync.com%3A6969","seeders":0,"leechers":0,"uploader":"xxxlavalxxx","files":4,"time":1450122693,"description":"http://extraimago.com/image/XpI\r\n\r\n \nhttp://www.rottentomatoes.com/m/marvel_super_hero_adventures_frost_fight/\r\n\r\n\r\nThe Marvel Heroes unite to try and stop Loki and the frost giant Ymir from conquering the world as the duo try to steal Santa's powers to do so.\r\n\r\nWritten By: Mark Banker\r\nProducers: Alan Fine, Dan Buckley, Joe Quesada, Jeph Loeb, Stan Lee, Eric Radomski, Cort Lane, Stephen Wacker\r\nActors: Mick Wingert, Matthew Mercer, Travis Willingham, Fred Tatasciore, Grey Griffin, Troy Baker, Antony Del Rio, Trevor Devall, Kevin Michael Richardson, Steve Blum, Jane Singer\r\n\r\n\r\nRELEASE: Marvel.Super.Hero.Adventures.Frost.2015.HDRip.XviD.AC3-EVO\r\n                                            \r\nSOURCE: 720p - Thanks KING-DVD!                                               \r\n\r\nViDEO: 2300 kbps XviD               \r\n\r\nRESOLUTiON: 720x400                           \r\n\r\nRUNTiME: 1h13m33sec      \r\n\r\nSUBTiTLES: N/A                               \r\n\r\nAUDiO: 384 Kbps AC3        \r\n\r\nLANGUAGE: ENGLiSH                                    \r\n\r\nNOTES: Enjoy.\r\n\r\nSPECIAL THANKS TO: The Big Boss WIGWIG, ANSA, ACHOSINK,\r\n                HAMADA, MAZENTBT, CD-Moonlight. \r\n \nhttp://extraimago.com/image/Xp3 \nhttp://extraimago.com/image/Xp9 \nhttp://extraimago.com/image/XpM \nhttp://extraimago.com/image/XpU","torrent":{"xt":"urn:btih:5bc1ee37caa97f7b9ea10fe65ed5ead0c878d7e8","amp;dn":"Marvel.Super.Hero.Adventures.Frost.2015.HDRip.XviD.AC3-EVO","amp;tr":["udp%3A%2F%2Ftracker.leechers-paradise.org%3A6969","udp%3A%2F%2Fzer0day.ch%3A1337","udp%3A%2F%2Fopen.demonii.com%3A1337","udp%3A%2F%2Ftracker.coppersurfer.tk%3A6969","udp%3A%2F%2Fexodus.desync.com%3A6969"],"infoHash":"5bc1ee37caa97f7b9ea10fe65ed5ead0c878d7e8","infoHashBuffer":{"type":"Buffer","data":[91,193,238,55,202,169,127,123,158,161,15,230,94,213,234,208,200,120,215,232]},"announce":[],"urlList":[]}}