{"title":"01 Made For This.mp3","uid":12782282,"size":4448407,"categoryP":"audio","categoryS":"music","magnet":"?xt=urn:btih:5e0262e0125131f6b2ba3d0f919a41c93aafcd61&amp;dn=01+Made+For+This.mp3&amp;tr=udp%3A%2F%2Ftracker.leechers-paradise.org%3A6969&amp;tr=udp%3A%2F%2Fzer0day.ch%3A1337&amp;tr=udp%3A%2F%2Fopen.demonii.com%3A1337&amp;tr=udp%3A%2F%2Ftracker.coppersurfer.tk%3A6969&amp;tr=udp%3A%2F%2Fexodus.desync.com%3A6969","seeders":0,"leechers":0,"uploader":null,"files":1,"time":1447805625,"description":"enjoy and seed","torrent":{"xt":"urn:btih:5e0262e0125131f6b2ba3d0f919a41c93aafcd61","amp;dn":"01+Made+For+This.mp3","amp;tr":["udp%3A%2F%2Ftracker.leechers-paradise.org%3A6969","udp%3A%2F%2Fzer0day.ch%3A1337","udp%3A%2F%2Fopen.demonii.com%3A1337","udp%3A%2F%2Ftracker.coppersurfer.tk%3A6969","udp%3A%2F%2Fexodus.desync.com%3A6969"],"infoHash":"5e0262e0125131f6b2ba3d0f919a41c93aafcd61","infoHashBuffer":{"type":"Buffer","data":[94,2,98,224,18,81,49,246,178,186,61,15,145,154,65,201,58,175,205,97]},"announce":[],"urlList":[]}}