{"title":"The.Flash.2014.S02E04.XviD-AFG","uid":12641497,"size":490534050,"categoryP":"video","categoryS":"tv_shows","magnet":"?xt=urn:btih:6ff01d279e7f3ee5ed714d7230ff3d9b501b3db0&amp;dn=The.Flash.2014.S02E04.XviD-AFG&amp;tr=udp%3A%2F%2Ftracker.leechers-paradise.org%3A6969&amp;tr=udp%3A%2F%2Fzer0day.ch%3A1337&amp;tr=udp%3A%2F%2Fopen.demonii.com%3A1337&amp;tr=udp%3A%2F%2Ftracker.coppersurfer.tk%3A6969&amp;tr=udp%3A%2F%2Fexodus.desync.com%3A6969","seeders":0,"leechers":0,"uploader":"TvTeam","files":12,"time":1445999384,"description":"------------------------------------------------------------------------\r\n\r  https://www.torrenting.com\r\n\r\nSign up is OPEN - for time being. Come and have fun.\r\n\r\n------------------------------------------------------------------------\r\n.[Title] The.Flash.2014.S02E04.XviD-AFG [/Title] \r\n\r\n[pre][b][color=red] The.Flash.2014.S02E04.XviD-AFG.avi [/color][/b]\r\n\r\n Duration          : 00:42:03 \r\n Release size      : 465 MB \r\n Video Bitrate     : 1 407 Kbps \r\n Frame rate        : 23.976 Fps  \r\n MP3 2ch CBR       : 128 kbps \r\n Video resolution  : 640x360  (16:9) \r\n\r\n[","torrent":{"xt":"urn:btih:6ff01d279e7f3ee5ed714d7230ff3d9b501b3db0","amp;dn":"The.Flash.2014.S02E04.XviD-AFG","amp;tr":["udp%3A%2F%2Ftracker.leechers-paradise.org%3A6969","udp%3A%2F%2Fzer0day.ch%3A1337","udp%3A%2F%2Fopen.demonii.com%3A1337","udp%3A%2F%2Ftracker.coppersurfer.tk%3A6969","udp%3A%2F%2Fexodus.desync.com%3A6969"],"infoHash":"6ff01d279e7f3ee5ed714d7230ff3d9b501b3db0","infoHashBuffer":{"type":"Buffer","data":[111,240,29,39,158,127,62,229,237,113,77,114,48,255,61,155,80,27,61,176]},"announce":[],"urlList":[]}}