{"title":"BoobDay.Ava.Addams.Neighborly.Fuckability","uid":12873607,"size":1587907854,"categoryP":"porn","categoryS":"movies","magnet":"?xt=urn:btih:716825aaf66038d63a10ef8638761fee3c9c486b&amp;dn=BoobDay.Ava.Addams.Neighborly.Fuckability&amp;tr=udp%3A%2F%2Ftracker.leechers-paradise.org%3A6969&amp;tr=udp%3A%2F%2Fzer0day.ch%3A1337&amp;tr=udp%3A%2F%2Fopen.demonii.com%3A1337&amp;tr=udp%3A%2F%2Ftracker.coppersurfer.tk%3A6969&amp;tr=udp%3A%2F%2Fexodus.desync.com%3A6969","seeders":0,"leechers":0,"uploader":"jepsrmnt","files":1,"time":1448920231,"description":"BoobDay.Ava.Addams.Neighborly.Fuckability.XXX.1080p.MP4-KTR.BTY\r\n\r\npreview \nhttp://booooty.com/?v=BoobDay.Ava.Addams.Neighborly.Fuckability.XXX.1080p.MP4-KTR.BTY_s.jpg","torrent":{"xt":"urn:btih:716825aaf66038d63a10ef8638761fee3c9c486b","amp;dn":"BoobDay.Ava.Addams.Neighborly.Fuckability","amp;tr":["udp%3A%2F%2Ftracker.leechers-paradise.org%3A6969","udp%3A%2F%2Fzer0day.ch%3A1337","udp%3A%2F%2Fopen.demonii.com%3A1337","udp%3A%2F%2Ftracker.coppersurfer.tk%3A6969","udp%3A%2F%2Fexodus.desync.com%3A6969"],"infoHash":"716825aaf66038d63a10ef8638761fee3c9c486b","infoHashBuffer":{"type":"Buffer","data":[113,104,37,170,246,96,56,214,58,16,239,134,56,118,31,238,60,156,72,107]},"announce":[],"urlList":[]}}