{"title":"Cruel Punishments - New Mistress Loves The Game - Full.mp4","uid":12926369,"size":831824819,"categoryP":"porn","categoryS":"movie_clips","magnet":"?xt=urn:btih:76c89b705d685e71a692d1d8908ed5267ad00803&amp;dn=Cruel+Punishments+-+New+Mistress+Loves+The+Game+-+Full.mp4&amp;tr=udp%3A%2F%2Ftracker.leechers-paradise.org%3A6969&amp;tr=udp%3A%2F%2Fzer0day.ch%3A1337&amp;tr=udp%3A%2F%2Fopen.demonii.com%3A1337&amp;tr=udp%3A%2F%2Ftracker.coppersurfer.tk%3A6969&amp;tr=udp%3A%2F%2Fexodus.desync.com%3A6969","seeders":0,"leechers":1,"uploader":"Piratepr0n","files":1,"time":1449474630,"description":"-------------------------------------------------------------------------------------\nName:\nCruel Punishments - New Mistress Loves The Game - Full.mp4\n-------------------------------------------------------------------------------------\nFile list:\nCruel Punishments - New Mistress Loves The Game - Full.mp4 (793 MiB | 720x404 | 47min 13s | MPEG-4) \nhttp://imgfapper.com/img-56652c33ad1a7.html","torrent":{"xt":"urn:btih:76c89b705d685e71a692d1d8908ed5267ad00803","amp;dn":"Cruel+Punishments+-+New+Mistress+Loves+The+Game+-+Full.mp4","amp;tr":["udp%3A%2F%2Ftracker.leechers-paradise.org%3A6969","udp%3A%2F%2Fzer0day.ch%3A1337","udp%3A%2F%2Fopen.demonii.com%3A1337","udp%3A%2F%2Ftracker.coppersurfer.tk%3A6969","udp%3A%2F%2Fexodus.desync.com%3A6969"],"infoHash":"76c89b705d685e71a692d1d8908ed5267ad00803","infoHashBuffer":{"type":"Buffer","data":[118,200,155,112,93,104,94,113,166,146,209,216,144,142,213,38,122,208,8,3]},"announce":[],"urlList":[]}}