{"title":"My.First.Sex.Teacher.Ariana.Marie.Gigi.Allens.XXX.BTY.mp4","uid":12807311,"size":717461515,"categoryP":"porn","categoryS":"movies","magnet":"?xt=urn:btih:836fac145da2174b0b3f3d8e0707a963498f95ec&amp;dn=My.First.Sex.Teacher.Ariana.Marie.Gigi.Allens.XXX.BTY.mp4&amp;tr=udp%3A%2F%2Ftracker.leechers-paradise.org%3A6969&amp;tr=udp%3A%2F%2Fzer0day.ch%3A1337&amp;tr=udp%3A%2F%2Fopen.demonii.com%3A1337&amp;tr=udp%3A%2F%2Ftracker.coppersurfer.tk%3A6969&amp;tr=udp%3A%2F%2Fexodus.desync.com%3A6969","seeders":0,"leechers":0,"uploader":"jepsrmnt","files":1,"time":1448138119,"description":"My.First.Sex.Teacher.Ariana.Marie.Gigi.Allens.XXX.BTY\r\n\r\npreview \nhttp://booooty.com/?v=My.First.Sex.Teacher.Ariana.Marie.Gigi.Allens.XXX.BTY_s.jpg","torrent":{"xt":"urn:btih:836fac145da2174b0b3f3d8e0707a963498f95ec","amp;dn":"My.First.Sex.Teacher.Ariana.Marie.Gigi.Allens.XXX.BTY.mp4","amp;tr":["udp%3A%2F%2Ftracker.leechers-paradise.org%3A6969","udp%3A%2F%2Fzer0day.ch%3A1337","udp%3A%2F%2Fopen.demonii.com%3A1337","udp%3A%2F%2Ftracker.coppersurfer.tk%3A6969","udp%3A%2F%2Fexodus.desync.com%3A6969"],"infoHash":"836fac145da2174b0b3f3d8e0707a963498f95ec","infoHashBuffer":{"type":"Buffer","data":[131,111,172,20,93,162,23,75,11,63,61,142,7,7,169,99,73,143,149,236]},"announce":[],"urlList":[]}}