{"title":"[RealWifeStories] Ava Addams (Double Timing Wife) [XXX]","uid":12874436,"size":609360365,"categoryP":"porn","categoryS":"movie_clips","magnet":"?xt=urn:btih:87c36651a7ea356aaee08fb185c5fdc521ee32b1&amp;dn=%5BRealWifeStories%5D+Ava+Addams+%28Double+Timing+Wife%29+%5BXXX%5D&amp;tr=udp%3A%2F%2Ftracker.leechers-paradise.org%3A6969&amp;tr=udp%3A%2F%2Fzer0day.ch%3A1337&amp;tr=udp%3A%2F%2Fopen.demonii.com%3A1337&amp;tr=udp%3A%2F%2Ftracker.coppersurfer.tk%3A6969&amp;tr=udp%3A%2F%2Fexodus.desync.com%3A6969","seeders":0,"leechers":0,"uploader":"Piratepr0n","files":1,"time":1448930855,"description":"-------------------------------------------------------------------------------------\nName:\n[RealWifeStories] Ava Addams (Double Timing Wife) [XXX]\n-------------------------------------------------------------------------------------\nFile list:\nrws_ava_addams_480p_2000.mp4 (581 MiB | 854x480 | 36min 20s | MPEG-4) \nhttp://imgfapper.com/img-565ce011e01ea.html","torrent":{"xt":"urn:btih:87c36651a7ea356aaee08fb185c5fdc521ee32b1","amp;dn":"%5BRealWifeStories%5D+Ava+Addams+%28Double+Timing+Wife%29+%5BXXX%5D","amp;tr":["udp%3A%2F%2Ftracker.leechers-paradise.org%3A6969","udp%3A%2F%2Fzer0day.ch%3A1337","udp%3A%2F%2Fopen.demonii.com%3A1337","udp%3A%2F%2Ftracker.coppersurfer.tk%3A6969","udp%3A%2F%2Fexodus.desync.com%3A6969"],"infoHash":"87c36651a7ea356aaee08fb185c5fdc521ee32b1","infoHashBuffer":{"type":"Buffer","data":[135,195,102,81,167,234,53,106,174,224,143,177,133,197,253,197,33,238,50,177]},"announce":[],"urlList":[]}}