{"title":"Busty girl gangbang as friends watch","uid":12771065,"size":116037320,"categoryP":"porn","categoryS":"movie_clips","magnet":"?xt=urn:btih:9125054d052558fabd3b0283382d6d8ff6038b25&amp;dn=Busty+girl+gangbang+as+friends+watch&amp;tr=udp%3A%2F%2Ftracker.leechers-paradise.org%3A6969&amp;tr=udp%3A%2F%2Fzer0day.ch%3A1337&amp;tr=udp%3A%2F%2Fopen.demonii.com%3A1337&amp;tr=udp%3A%2F%2Ftracker.coppersurfer.tk%3A6969&amp;tr=udp%3A%2F%2Fexodus.desync.com%3A6969","seeders":0,"leechers":1,"uploader":"demonoidt","files":1,"time":1447673870,"description":"Samples\r\n \nhttp://adultwallpapers.co.in/busty-girl-gangbang-as-friends-watch/\r\n \nhttp://adultwallpapers.co.in/busty-girl-gangbang-as-friends-watch-2/\r\n \nhttp://adultwallpapers.co.in/busty-girl-gangbang-as-friends-watch-3/\r\n \nhttp://demonoid.co/2015/11/16/busty-girl-gangbang-as-friends-watch/","torrent":{"xt":"urn:btih:9125054d052558fabd3b0283382d6d8ff6038b25","amp;dn":"Busty+girl+gangbang+as+friends+watch","amp;tr":["udp%3A%2F%2Ftracker.leechers-paradise.org%3A6969","udp%3A%2F%2Fzer0day.ch%3A1337","udp%3A%2F%2Fopen.demonii.com%3A1337","udp%3A%2F%2Ftracker.coppersurfer.tk%3A6969","udp%3A%2F%2Fexodus.desync.com%3A6969"],"infoHash":"9125054d052558fabd3b0283382d6d8ff6038b25","infoHashBuffer":{"type":"Buffer","data":[145,37,5,77,5,37,88,250,189,59,2,131,56,45,109,143,246,3,139,37]},"announce":[],"urlList":[]}}