{"title":"[Brazzers] - DoctorAdventures - Julia Ann - [December 10, 2015]","uid":12951607,"size":313797012,"categoryP":"porn","categoryS":"movie_clips","magnet":"?xt=urn:btih:9589e8d61f8f811243007aba19b9609eaa747c52&amp;dn=%5BBrazzers%5D+-+DoctorAdventures+-+Julia+Ann+-+%5BDecember+10%2C+2015%5D&amp;tr=udp%3A%2F%2Ftracker.leechers-paradise.org%3A6969&amp;tr=udp%3A%2F%2Fzer0day.ch%3A1337&amp;tr=udp%3A%2F%2Fopen.demonii.com%3A1337&amp;tr=udp%3A%2F%2Ftracker.coppersurfer.tk%3A6969&amp;tr=udp%3A%2F%2Fexodus.desync.com%3A6969","seeders":0,"leechers":1,"uploader":"TheSgrt","files":1,"time":1449735421,"description":"Screenshots:\r\n \nhttp://xxximages.co/img-5669260f84924.html\r\n\r\nDescription:\r\n\r\nDanny D takes his girlfriend to the doctor’s office for a check-up, where a sexy nurse (Julia Ann) will perform the exam. The nurse flirts with Danny, who tries to quell his girlfriend’s worries of needles. When the nurse is about to inject the needle, she passes out. Naughty nurse Julia Ann then seduces Mr. D and they fuck while his girlfriend is dosing off! This sexy nurse sure knows how to get the cock pumpin'!\r\n\r\n[Brazzers] - DoctorAdventures - Julia Ann - Hot Nurse Gets The Cock Pumpin - [December 10, 2015 - APT].mp4","torrent":{"xt":"urn:btih:9589e8d61f8f811243007aba19b9609eaa747c52","amp;dn":"%5BBrazzers%5D+-+DoctorAdventures+-+Julia+Ann+-+%5BDecember+10%2C+2015%5D","amp;tr":["udp%3A%2F%2Ftracker.leechers-paradise.org%3A6969","udp%3A%2F%2Fzer0day.ch%3A1337","udp%3A%2F%2Fopen.demonii.com%3A1337","udp%3A%2F%2Ftracker.coppersurfer.tk%3A6969","udp%3A%2F%2Fexodus.desync.com%3A6969"],"infoHash":"9589e8d61f8f811243007aba19b9609eaa747c52","infoHashBuffer":{"type":"Buffer","data":[149,137,232,214,31,143,129,18,67,0,122,186,25,185,96,158,170,116,124,82]},"announce":[],"urlList":[]}}