{"title":"KellyMadison - Kelly Madison (Posing for the art of it) 04-Decem","uid":12930181,"size":549331766,"categoryP":"porn","categoryS":"movie_clips","magnet":"?xt=urn:btih:98dd2ab27637904df3a7c1a18f4841424f3522df&amp;dn=KellyMadison+-+Kelly+Madison+%28Posing+for+the+art+of+it%29+04-Decem&amp;tr=udp%3A%2F%2Ftracker.leechers-paradise.org%3A6969&amp;tr=udp%3A%2F%2Fzer0day.ch%3A1337&amp;tr=udp%3A%2F%2Fopen.demonii.com%3A1337&amp;tr=udp%3A%2F%2Ftracker.coppersurfer.tk%3A6969&amp;tr=udp%3A%2F%2Fexodus.desync.com%3A6969","seeders":0,"leechers":0,"uploader":"Piratepr0n","files":1,"time":1449514541,"description":"-------------------------------------------------------------------------------------\nName:\nKellyMadison - Kelly Madison (Posing for the art of it) 04-December-2015\n-------------------------------------------------------------------------------------\nFile list:\nKellyMadison - Kelly Madison (Posing for the art of it) 04-December-2015.mp4 (524 MiB | 852x480 | 26min 8s | MPEG-4) \nhttp://imgfapper.com/img-5665c81ac1ecb.html","torrent":{"xt":"urn:btih:98dd2ab27637904df3a7c1a18f4841424f3522df","amp;dn":"KellyMadison+-+Kelly+Madison+%28Posing+for+the+art+of+it%29+04-Decem","amp;tr":["udp%3A%2F%2Ftracker.leechers-paradise.org%3A6969","udp%3A%2F%2Fzer0day.ch%3A1337","udp%3A%2F%2Fopen.demonii.com%3A1337","udp%3A%2F%2Ftracker.coppersurfer.tk%3A6969","udp%3A%2F%2Fexodus.desync.com%3A6969"],"infoHash":"98dd2ab27637904df3a7c1a18f4841424f3522df","infoHashBuffer":{"type":"Buffer","data":[152,221,42,178,118,55,144,77,243,167,193,161,143,72,65,66,79,53,34,223]},"announce":[],"urlList":[]}}