{"title":"Talking.Dead.S06E04.720p.HDTV.x264-BATV[cttv]","uid":12675706,"size":1174856856,"categoryP":"video","categoryS":"hd___tv_shows","magnet":"?xt=urn:btih:a09cd1af1ccb923f5cc11ad0cac99c20d0495d20&amp;dn=Talking.Dead.S06E04.720p.HDTV.x264-BATV%5Bcttv%5D&amp;tr=udp%3A%2F%2Ftracker.leechers-paradise.org%3A6969&amp;tr=udp%3A%2F%2Fzer0day.ch%3A1337&amp;tr=udp%3A%2F%2Fopen.demonii.com%3A1337&amp;tr=udp%3A%2F%2Ftracker.coppersurfer.tk%3A6969&amp;tr=udp%3A%2F%2Fexodus.desync.com%3A6969","seeders":0,"leechers":0,"uploader":"maximersk","files":3,"time":1446501850,"description":"Talking.Dead.S06E04.720p.HDTV.x264-BATV[cttv]\r\n\r\n\r\n\r\n\r\n\r\n[Format]: MKV \r\n[Resolution]: 720p \r\n[Display aspect ratio]: 16:9 \r\n[Frame rate]: 23.976 fps","torrent":{"xt":"urn:btih:a09cd1af1ccb923f5cc11ad0cac99c20d0495d20","amp;dn":"Talking.Dead.S06E04.720p.HDTV.x264-BATV%5Bcttv%5D","amp;tr":["udp%3A%2F%2Ftracker.leechers-paradise.org%3A6969","udp%3A%2F%2Fzer0day.ch%3A1337","udp%3A%2F%2Fopen.demonii.com%3A1337","udp%3A%2F%2Ftracker.coppersurfer.tk%3A6969","udp%3A%2F%2Fexodus.desync.com%3A6969"],"infoHash":"a09cd1af1ccb923f5cc11ad0cac99c20d0495d20","infoHashBuffer":{"type":"Buffer","data":[160,156,209,175,28,203,146,63,92,193,26,208,202,201,156,32,208,73,93,32]},"announce":[],"urlList":[]}}