{"title":"ArchAngelVideo.Amirah.Adara.Amirah.Adara.Anal.Fucking.mp4","uid":12942708,"size":841806574,"categoryP":"porn","categoryS":"movie_clips","magnet":"?xt=urn:btih:adc0a1d6dd848cb21574befcc775bf7c5dbfe637&amp;dn=ArchAngelVideo.Amirah.Adara.Amirah.Adara.Anal.Fucking.mp4&amp;tr=udp%3A%2F%2Ftracker.leechers-paradise.org%3A6969&amp;tr=udp%3A%2F%2Fzer0day.ch%3A1337&amp;tr=udp%3A%2F%2Fopen.demonii.com%3A1337&amp;tr=udp%3A%2F%2Ftracker.coppersurfer.tk%3A6969&amp;tr=udp%3A%2F%2Fexodus.desync.com%3A6969","seeders":0,"leechers":0,"uploader":"SexPR","files":3,"time":1449641562,"description":"SCREENSHOTS \nhttp://imgstylo.site/image/jl \nhttp://imgstylo.site/image/j4","torrent":{"xt":"urn:btih:adc0a1d6dd848cb21574befcc775bf7c5dbfe637","amp;dn":"ArchAngelVideo.Amirah.Adara.Amirah.Adara.Anal.Fucking.mp4","amp;tr":["udp%3A%2F%2Ftracker.leechers-paradise.org%3A6969","udp%3A%2F%2Fzer0day.ch%3A1337","udp%3A%2F%2Fopen.demonii.com%3A1337","udp%3A%2F%2Ftracker.coppersurfer.tk%3A6969","udp%3A%2F%2Fexodus.desync.com%3A6969"],"infoHash":"adc0a1d6dd848cb21574befcc775bf7c5dbfe637","infoHashBuffer":{"type":"Buffer","data":[173,192,161,214,221,132,140,178,21,116,190,252,199,117,191,124,93,191,230,55]},"announce":[],"urlList":[]}}