{"title":"Slim body and hot big Boobs","uid":12955095,"size":25006454,"categoryP":"porn","categoryS":"pictures","magnet":"?xt=urn:btih:b7bcd9e9d34b51699acaad0db5f1878b9486cce7&amp;dn=Slim+body+and+hot+big+Boobs&amp;tr=udp%3A%2F%2Ftracker.leechers-paradise.org%3A6969&amp;tr=udp%3A%2F%2Fzer0day.ch%3A1337&amp;tr=udp%3A%2F%2Fopen.demonii.com%3A1337&amp;tr=udp%3A%2F%2Ftracker.coppersurfer.tk%3A6969&amp;tr=udp%3A%2F%2Fexodus.desync.com%3A6969","seeders":0,"leechers":1,"uploader":"expressfile","files":47,"time":1449772824,"description":"Slim body and hot big Boobs\r\n \nhttp://leechimg.com/image/3Kh7\r\n \nhttp://leechimg.com/image/3KhA\r\n \nhttp://leechimg.com/image/3Khl\r\n\r\n23.8 Mb - 47 Pictures\r\n\r\nPlease seed and enjoy\r\n\r\nCheck all my torrents\r\n  \nhttp://thepiratebay.se/user/expressfile/","torrent":{"xt":"urn:btih:b7bcd9e9d34b51699acaad0db5f1878b9486cce7","amp;dn":"Slim+body+and+hot+big+Boobs","amp;tr":["udp%3A%2F%2Ftracker.leechers-paradise.org%3A6969","udp%3A%2F%2Fzer0day.ch%3A1337","udp%3A%2F%2Fopen.demonii.com%3A1337","udp%3A%2F%2Ftracker.coppersurfer.tk%3A6969","udp%3A%2F%2Fexodus.desync.com%3A6969"],"infoHash":"b7bcd9e9d34b51699acaad0db5f1878b9486cce7","infoHashBuffer":{"type":"Buffer","data":[183,188,217,233,211,75,81,105,154,202,173,13,181,241,135,139,148,134,204,231]},"announce":[],"urlList":[]}}