{"title":"GirlsDoPorn.E340.18.Years.Old.XXX.720p.MP4-KTR[N1C]","uid":12708758,"size":1251061168,"categoryP":"porn","categoryS":"other","magnet":"?xt=urn:btih:bcf8b9a1333f2bb03dc3bab6a3c5a7e3fe8be685&amp;dn=GirlsDoPorn.E340.18.Years.Old.XXX.720p.MP4-KTR%5BN1C%5D&amp;tr=udp%3A%2F%2Ftracker.leechers-paradise.org%3A6969&amp;tr=udp%3A%2F%2Fzer0day.ch%3A1337&amp;tr=udp%3A%2F%2Fopen.demonii.com%3A1337&amp;tr=udp%3A%2F%2Ftracker.coppersurfer.tk%3A6969&amp;tr=udp%3A%2F%2Fexodus.desync.com%3A6969","seeders":0,"leechers":2,"uploader":"juggs99","files":2,"time":1446873076,"description":"\n                        \n                        GirlsDoPorn.E340.18.Years.Old.XXX.720p.MP4-KTR \r\n\n                        \n                        [Format]:    MPEG-4\n[Duration]:    44mn 13s\n[Resolution]:  1 280 x 720 pixels\n[Display aspect ratio]:    16:9\n[Frame rate mode]:    Constant\n[Frame rate]:    29.970 fps\n\r\n\n                        \n#NO1CARES -&gt; To avoid fakes, ALWAYS check that the torrent was added by NO1CARES\r\n \nhttp://extratorrent.cc/\r\n\n\nHelp us by donating with Bitcoin: 1XeH1kKXWYbzZcFHokGiZ4d3MWW5WyXzU\r\n\nScreens...\r \nhttp://HotImage.uk/img-563d7535bd1df.html\r\n  \nhttp://HotImage.uk/img-563d7535c7de7.html\r \nhttp://HotImage.uk/img-563d7535d1fc9.html\r \nhttp://HotImage.uk/img-563d7535dc258.html","torrent":{"xt":"urn:btih:bcf8b9a1333f2bb03dc3bab6a3c5a7e3fe8be685","amp;dn":"GirlsDoPorn.E340.18.Years.Old.XXX.720p.MP4-KTR%5BN1C%5D","amp;tr":["udp%3A%2F%2Ftracker.leechers-paradise.org%3A6969","udp%3A%2F%2Fzer0day.ch%3A1337","udp%3A%2F%2Fopen.demonii.com%3A1337","udp%3A%2F%2Ftracker.coppersurfer.tk%3A6969","udp%3A%2F%2Fexodus.desync.com%3A6969"],"infoHash":"bcf8b9a1333f2bb03dc3bab6a3c5a7e3fe8be685","infoHashBuffer":{"type":"Buffer","data":[188,248,185,161,51,63,43,176,61,195,186,182,163,197,167,227,254,139,230,133]},"announce":[],"urlList":[]}}