{"title":"EvilAngel.Nikki.S.Nacho.s.Street.Legal.Scene.3","uid":12991009,"size":312003845,"categoryP":"porn","categoryS":"movie_clips","magnet":"?xt=urn:btih:bf6182365eeef84d9778c24cc54c8a3d57deb2dd&amp;dn=EvilAngel.Nikki.S.Nacho.s.Street.Legal.Scene.3&amp;tr=udp%3A%2F%2Ftracker.leechers-paradise.org%3A6969&amp;tr=udp%3A%2F%2Fzer0day.ch%3A1337&amp;tr=udp%3A%2F%2Fopen.demonii.com%3A1337&amp;tr=udp%3A%2F%2Ftracker.coppersurfer.tk%3A6969&amp;tr=udp%3A%2F%2Fexodus.desync.com%3A6969","seeders":0,"leechers":0,"uploader":"SexPR","files":3,"time":1450124551,"description":"SCREENSHOTS \nhttp://imgstylo.site/image/Aa \nhttp://imgstylo.site/image/Aj\r\n\r\nMY COLLECTIONS \nhttps://thepiratebay.mn/user/SexPR","torrent":{"xt":"urn:btih:bf6182365eeef84d9778c24cc54c8a3d57deb2dd","amp;dn":"EvilAngel.Nikki.S.Nacho.s.Street.Legal.Scene.3","amp;tr":["udp%3A%2F%2Ftracker.leechers-paradise.org%3A6969","udp%3A%2F%2Fzer0day.ch%3A1337","udp%3A%2F%2Fopen.demonii.com%3A1337","udp%3A%2F%2Ftracker.coppersurfer.tk%3A6969","udp%3A%2F%2Fexodus.desync.com%3A6969"],"infoHash":"bf6182365eeef84d9778c24cc54c8a3d57deb2dd","infoHashBuffer":{"type":"Buffer","data":[191,97,130,54,94,238,248,77,151,120,194,76,197,76,138,61,87,222,178,221]},"announce":[],"urlList":[]}}