{"title":"GIGL-267.mp4","uid":13680337,"size":2384868989,"categoryP":"porn","categoryS":"movie_clips","magnet":"?xt=urn:btih:c6b224c37efe9b7cf8c866d3a48d2c002f437ec9&amp;dn=GIGL-267.mp4&amp;tr=udp%3A%2F%2Ftracker.leechers-paradise.org%3A6969&amp;tr=udp%3A%2F%2Fzer0day.ch%3A1337&amp;tr=udp%3A%2F%2Fopen.demonii.com%3A1337&amp;tr=udp%3A%2F%2Ftracker.coppersurfer.tk%3A6969&amp;tr=udp%3A%2F%2Fexodus.desync.com%3A6969","seeders":0,"leechers":0,"uploader":"Piratepr0n","files":1,"time":1456455879,"description":"-------------------------------------------------------------------------------------\nName:\nGIGL-267.mp4\n-------------------------------------------------------------------------------------\nFile list:\nGIGL-267.mp4 (2.22 GiB | 856x480 | 3h 59min | MPEG-4) \nhttp://imgfapper.com/img-56cfb2afa3f93.html","torrent":{"xt":"urn:btih:c6b224c37efe9b7cf8c866d3a48d2c002f437ec9","amp;dn":"GIGL-267.mp4","amp;tr":["udp%3A%2F%2Ftracker.leechers-paradise.org%3A6969","udp%3A%2F%2Fzer0day.ch%3A1337","udp%3A%2F%2Fopen.demonii.com%3A1337","udp%3A%2F%2Ftracker.coppersurfer.tk%3A6969","udp%3A%2F%2Fexodus.desync.com%3A6969"],"infoHash":"c6b224c37efe9b7cf8c866d3a48d2c002f437ec9","infoHashBuffer":{"type":"Buffer","data":[198,178,36,195,126,254,155,124,248,200,102,211,164,141,44,0,47,67,126,201]},"announce":[],"urlList":[]}}