{"title":"[Evil Angel] Dirty Talk [2015-12][MP4][960x544][Split Scenes]","uid":12930841,"size":2401898537,"categoryP":"porn","categoryS":"movies","magnet":"?xt=urn:btih:e99e942edfaa73cd7c301857981beb6e55c5d5b5&amp;dn=%5BEvil+Angel%5D+Dirty+Talk+%5B2015-12%5D%5BMP4%5D%5B960x544%5D%5BSplit+Scenes%5D&amp;tr=udp%3A%2F%2Ftracker.leechers-paradise.org%3A6969&amp;tr=udp%3A%2F%2Fzer0day.ch%3A1337&amp;tr=udp%3A%2F%2Fopen.demonii.com%3A1337&amp;tr=udp%3A%2F%2Ftracker.coppersurfer.tk%3A6969&amp;tr=udp%3A%2F%2Fexodus.desync.com%3A6969","seeders":0,"leechers":0,"uploader":"Piratepr0n","files":4,"time":1449523309,"description":"-------------------------------------------------------------------------------------\nName:\n[Evil Angel] Dirty Talk [2015-12][MP4][960x544][Split Scenes]\n-------------------------------------------------------------------------------------\nFile list:\n30672_01_hd.mp4 (686 MiB | 960x544 | 53min 52s | MPEG-4) \nhttp://imgfapper.com/img-5665ea4fe76fd.html \n\n30672_02_hd.mp4 (716 MiB | 960x544 | 52min 52s | MPEG-4) \nhttp://imgfapper.com/img-5665ea5244e8f.html \n\n30672_03_hd.mp4 (451 MiB | 960x544 | 38min 2s | MPEG-4) \nhttp://imgfapper.com/img-5665ea548aeb6.html \n\n30672_04_hd.mp4 (437 MiB | 960x544 | 33min 34s | MPEG-4) \nhttp://imgfapper.com/img-5665ea56d6ea0.html","torrent":{"xt":"urn:btih:e99e942edfaa73cd7c301857981beb6e55c5d5b5","amp;dn":"%5BEvil+Angel%5D+Dirty+Talk+%5B2015-12%5D%5BMP4%5D%5B960x544%5D%5BSplit+Scenes%5D","amp;tr":["udp%3A%2F%2Ftracker.leechers-paradise.org%3A6969","udp%3A%2F%2Fzer0day.ch%3A1337","udp%3A%2F%2Fopen.demonii.com%3A1337","udp%3A%2F%2Ftracker.coppersurfer.tk%3A6969","udp%3A%2F%2Fexodus.desync.com%3A6969"],"infoHash":"e99e942edfaa73cd7c301857981beb6e55c5d5b5","infoHashBuffer":{"type":"Buffer","data":[233,158,148,46,223,170,115,205,124,48,24,87,152,27,235,110,85,197,213,181]},"announce":[],"urlList":[]}}