{"title":"bblib_carmella_shyla_480p_2200.wmv","uid":12910149,"size":383082868,"categoryP":"porn","categoryS":"movie_clips","magnet":"?xt=urn:btih:f8fb36790c7c85c3485364ee591c84b6e6141c11&amp;dn=bblib_carmella_shyla_480p_2200.wmv&amp;tr=udp%3A%2F%2Ftracker.leechers-paradise.org%3A6969&amp;tr=udp%3A%2F%2Fzer0day.ch%3A1337&amp;tr=udp%3A%2F%2Fopen.demonii.com%3A1337&amp;tr=udp%3A%2F%2Ftracker.coppersurfer.tk%3A6969&amp;tr=udp%3A%2F%2Fexodus.desync.com%3A6969","seeders":0,"leechers":0,"uploader":"Piratepr0n","files":1,"time":1449288981,"description":"-------------------------------------------------------------------------------------\nName:\nbblib_carmella_shyla_480p_2200.wmv\n-------------------------------------------------------------------------------------\nFile list:\nbblib_carmella_shyla_480p_2200.wmv (365 MiB | 640x480 | 37min 25s | Windows Media) \nhttp://imgfapper.com/img-566257019b830.html","torrent":{"xt":"urn:btih:f8fb36790c7c85c3485364ee591c84b6e6141c11","amp;dn":"bblib_carmella_shyla_480p_2200.wmv","amp;tr":["udp%3A%2F%2Ftracker.leechers-paradise.org%3A6969","udp%3A%2F%2Fzer0day.ch%3A1337","udp%3A%2F%2Fopen.demonii.com%3A1337","udp%3A%2F%2Ftracker.coppersurfer.tk%3A6969","udp%3A%2F%2Fexodus.desync.com%3A6969"],"infoHash":"f8fb36790c7c85c3485364ee591c84b6e6141c11","infoHashBuffer":{"type":"Buffer","data":[248,251,54,121,12,124,133,195,72,83,100,238,89,28,132,182,230,20,28,17]},"announce":[],"urlList":[]}}